<?xml version="1.0" encoding="utf-8" ?>
<Defs>

	<ResearchProjectDef>
		<defName>PRF_Carbon</defName>
		<label>Carbon Production</label>
		<description>Carbon is an abundant and mouldable material with countless applications, a precursor for many spacer materials.</description>
		<baseCost>400</baseCost>
		<techLevel>Medieval</techLevel>
		<tab>PRF_Materials</tab>
		<researchViewX>0.00</researchViewX>
		<researchViewY>4.20</researchViewY>
	</ResearchProjectDef>

	<ResearchProjectDef>
		<defName>PRF_CarbonNanotubes</defName>
		<label>Carbon Nanotube Production</label>
		<description>Microscopic tubes of carbon strung into a mesh makes for an extremely lightweight and durable material.</description>
		<baseCost>600</baseCost>
		<techLevel>Industrial</techLevel>
		<prerequisites>
			<li>PRF_Carbon</li>
			<li>Electricity</li>
		</prerequisites>
		<tab>PRF_Materials</tab>
		<researchViewX>1.00</researchViewX>
		<researchViewY>4.20</researchViewY>
	</ResearchProjectDef>

	<ResearchProjectDef>
		<defName>PRF_CarbonFiber</defName>
		<label>Carbon Fiber Production</label>
		<description>Weaving carbon into cloth and leathers provides incredible reinforcement and protection.</description>
		<baseCost>250</baseCost>
		<techLevel>Industrial</techLevel>
		<prerequisites>
			<li>PRF_CarbonNanotubes</li>
		</prerequisites>
		<tab>PRF_Materials</tab>
		<researchViewX>2.00</researchViewX>
		<researchViewY>4.20</researchViewY>
	</ResearchProjectDef>

	<ResearchProjectDef>
		<defName>PRF_CarbonKevlar</defName>
		<label>Advanced Carbon Fiber Production</label>
		<description>Learn how interweave carbon fiber with Kevlar to produce a defensive fabric.</description>
		<baseCost>750</baseCost>
		<techLevel>Spacer</techLevel>
		<prerequisites>
			<li>PRF_CarbonFiber</li>
		</prerequisites>
		<requiredResearchBuilding>HiTechResearchBench</requiredResearchBuilding>
		<tab>PRF_Materials</tab>
  <researchViewX>3.00</researchViewX>
  <researchViewY>4.15</researchViewY>
	</ResearchProjectDef>

	<ResearchProjectDef>
		<defName>PRF_CarbonPlating</defName>
		<label>Carbon Fiber Lamination</label>
		<description>Bonding carbon fiber with plastic materials creates a strong and light structural material.</description>
		<baseCost>500</baseCost>
		<techLevel>Industrial</techLevel>
		<prerequisites>
			<li>PRF_CarbonFiber</li>
		</prerequisites>
		<tab>PRF_Materials</tab>
		<researchViewX>3.00</researchViewX>
		<researchViewY>3.50</researchViewY>
	</ResearchProjectDef>

	<ResearchProjectDef>
		<defName>PRF_SyntheticDiamond</defName>
		<label>Diamond Synthesis</label>
		<description>Industrial diamonds can be synthesized from carbon fiber using heat and incredible pressure. This results in one of the strongest materials in nature.</description>
		<baseCost>1000</baseCost>
		<techLevel>Industrial</techLevel>
		<prerequisites>
			<li>PRF_CarbonFiber</li>
		</prerequisites>
		<requiredResearchBuilding>HiTechResearchBench</requiredResearchBuilding>
		<requiredResearchFacilities>
			<li>MultiAnalyzer</li>
			<li>PRF_ResearchTerminal</li>
		</requiredResearchFacilities>
		<tab>PRF_Materials</tab>
		<researchViewX>3.00</researchViewX>
		<researchViewY>2.95</researchViewY>
	</ResearchProjectDef>

</Defs>
