<?xml version="1.0" encoding="utf-8" ?>
<Defs>

  <ResearchProjectDef>
    <defName>PRF_Research_StainlessSteelAlloying</defName>
    <label>Alloying</label>
    <description>Alloy materials to create materials for industrial applications.</description>
    <baseCost>700</baseCost>
    <techLevel>Industrial</techLevel>
    <tab>PRF_Materials</tab>
  <researchViewX>1.00</researchViewX>
  <researchViewY>0.00</researchViewY>
    <prerequisites>
      <li>Smithing</li>
    </prerequisites>
  </ResearchProjectDef>

</Defs>
